preprocessor/__init__.py
preprocessor/core.py
preprocessor_qna-0.0.1.dist-info/METADATA
preprocessor_qna-0.0.1.dist-info/WHEEL
preprocessor_qna-0.0.1.dist-info/top_level.txt
preprocessor_qna-0.0.1.dist-info/RECORD
