Metadata-Version: 2.1
Name: preprocessor-qna
Version: 0.0.1
Summary: UNKNOWN
Home-page: UNKNOWN
Author: UNKNOWN
Author-email: UNKNOWN
License: UNKNOWN
Platform: UNKNOWN
Requires-Dist: base-processor (==0.0.2)
